cosmoscreen/__init__.py
cosmoscreen-0.0.1.dev1.dist-info/METADATA
cosmoscreen-0.0.1.dev1.dist-info/WHEEL
cosmoscreen-0.0.1.dev1.dist-info/top_level.txt
cosmoscreen-0.0.1.dev1.dist-info/RECORD
