Metadata-Version: 2.4
Name: cosmoscreen
Version: 0.0.1.dev1
Summary: COSMOScreen: COSMO-SAC-based phase equilibrium screening toolkit
Author-email: Your Name <you@example.com>
License: MIT
Requires-Python: >=3.8
